{"name":"build-javascript","namedChunkGroups":{"app":{"name":"app","assets":[{"name":"webpack-runtime-d82eadeb62defacd3a1a.js","size":4745},{"name":"framework-3e86e9eafe2c4004775b.js","size":140787},{"name":"app-547dc8418cee60e332f9.js","size":99807}],"filteredAssets":0,"assetsSize":245339,"filteredAuxiliaryAssets":3,"auxiliaryAssetsSize":713098},"component---src-pages-index-tsx":{"name":"component---src-pages-index-tsx","assets":[{"name":"component---src-pages-index-tsx-d20b17c50d83e614f922.js","size":2434}],"filteredAssets":0,"assetsSize":2434,"filteredAuxiliaryAssets":3,"auxiliaryAssetsSize":3699423},"component---src-pages-wedding-tsx":{"name":"component---src-pages-wedding-tsx","assets":[{"name":"styles.005c5ec248f506820266.css","size":96183},{"name":"component---src-pages-wedding-tsx-380bf597855b53fe8be8.js","size":32477}],"filteredAssets":0,"assetsSize":128660,"filteredAuxiliaryAssets":54,"auxiliaryAssetsSize":30090887}},"assetsByChunkName":{"app":["webpack-runtime-d82eadeb62defacd3a1a.js","framework-3e86e9eafe2c4004775b.js","app-547dc8418cee60e332f9.js"],"component---src-pages-index-tsx":["component---src-pages-index-tsx-d20b17c50d83e614f922.js"],"component---src-pages-wedding-tsx":["styles.005c5ec248f506820266.css","component---src-pages-wedding-tsx-380bf597855b53fe8be8.js"]},"childAssetsByChunkName":{}}